ctypesForFortran/__init__.py
ctypesforfortran-2.2.1.dist-info/licenses/LICENSE
ctypesforfortran-2.2.1.dist-info/METADATA
ctypesforfortran-2.2.1.dist-info/WHEEL
ctypesforfortran-2.2.1.dist-info/top_level.txt
ctypesforfortran-2.2.1.dist-info/RECORD
