Metadata-Version: 2.4
Name: ctypesForFortran
Version: 2.2.1
Summary: Bindings to Fortran subroutines using ctypes
Author-email: Sébastien Riette <sebastien.riette@meteo.fr>
Maintainer-email: Sébastien Riette <sebastien.riette@meteo.fr>
License: 
Project-URL: source, https://github.com/UMR-CNRM/ctypesForFortran.git
Project-URL: tracker, https://github.com/UMR-CNRM/ctypesForFortran/issues
Classifier: Development Status :: 5 - Production/Stable
Classifier: Intended Audience :: Science/Research
Classifier: Intended Audience :: Developers
Classifier: Programming Language :: Python
Classifier: Programming Language :: Python :: 3.6
Classifier: Programming Language :: Python :: 3.7
Classifier: Programming Language :: Python :: 3.8
Classifier: Programming Language :: Python :: 3.10
Classifier: Programming Language :: Python :: 3.11
Classifier: Programming Language :: Python :: 3.12
Classifier: Operating System :: Unix
Requires-Python: >=3.6
License-File: LICENSE
Requires-Dist: numpy
Dynamic: license-file
